[
  {
    "key": "ctrl+b ctrl+a",
    "command": "workbench.action.toggleActivityBarVisibility",
    "when": "!terminalFocus"
  },
  {
    "key": "ctrl+b ctrl+b",
    "command": "workbench.action.toggleSidebarVisibility",
    "when": "!terminalFocus"
  },
  {
    "key": "ctrl+b ctrl+e",
    "command": "workbench.view.explorer",
    "when": "!terminalFocus"
  },
  {
    "key": "ctrl+b ctrl+f",
    "commd": "workbench.action.findInFiles",
    "when": "!terminalFocus"
  },
  {
    "key": "ctrl+b ctrl+g",
    "command": "workbench.view.scm",
    "when": "!terminalFocus"
  },
  {
    "key": "ctrl+b ctrl+d",
    "command": "workbench.view.debug",
    "when": "!terminalFocus"
  },
  {
    "key": "ctrl+b ctrl+x",
    "command": "workbench.view.extensions",
    "when": "!terminalFocus"
  },
  {
    "key": "ctrl+n",
    "command": "selectNextSuggestion",
    "when": "suggestWidgetMultipleSuggestions && suggestWidgetVisible && textInputFocus"
  },
  {
    "key": "ctrl+shift+n",
    "command": "selectPrevSuggestion",
    "when": "suggestWidgetMultipleSuggestions && suggestWidgetVisible && textInputFocus"
  },
  {
    "key": "alt+l",
    "command": "workbench.action.increaseViewSize"
  },
  {
    "key": "alt+h",
    "command": "workbench.action.decreaseViewSize"
  },
  {
    "key": "alt+shift+j",
    "command": "workbench.action.moveActiveEditorGroupDown"
  },
  {
    "key": "alt+shift+h",
    "command": "workbench.action.moveActiveEditorGroupLeft"
  },
  {
    "key": "alt+shift+l",
    "command": "workbench.action.moveActiveEditorGroupRight"
  },
  {
    "key": "alt+shift+k",
    "command": "workbench.action.moveActiveEditorGroupUp"
  },
  {
    "command": "editor.action.moveLinesDownAction",
    "key": "alt+j",
    "when": "editorTextFocus && !editorReadonly"
  },
  {
    "key": "alt+k",
    "command": "editor.action.moveLinesUpAction",
    "when": "editorTextFocus && !editorReadonly"
  },
  {
    "key": "shift+alt+j",
    "command": "editor.action.copyLinesDownAction",
    "when": "editorTextFocus && !editorReadonly"
  },
  {
    "key": "shift+alt+k",
    "command": "editor.action.copyLinesUpAction",
    "when": "editorTextFocus && !editorReadonly"
  },
  {
    "key": "ctrl+p",
    "command": "workbench.action.quickOpen",
    "when": "!terminalFocus"
  },
  {
    "key": "ctrl+p",
    "command": "-workbench.action.quickOpen"
  },
  {
    "key": "ctrl+q",
    "command": "workbench.action.quit",
    "when": "!terminalFocus"
  },
  {
    "key": "ctrl+q",
    "command": "-workbench.action.quit"
  }
]